{
  "ethereum": {
    "last_block": 24773244,
    "stats": {
      "transfers": 23,
      "holders_gt10": 528
    }
  },
  "arbitrum": {
    "last_block": 447362702,
    "stats": {
      "transfers": 113,
      "holders_gt10": 125
    }
  },
  "polygon": {
    "last_block": 84892857,
    "stats": {
      "transfers": 3,
      "holders_gt10": 50
    }
  },
  "last_full_scan": "2026-03-29",
  "last_scan": "2026-03-30T22:01:22Z",
  "mode": "INCREMENTAL",
  "base": {
    "last_block": 44059363,
    "stats": {
      "transfers": 3404,
      "holders_gt10": 60
    }
  },
  "optimism": {
    "last_block": 149654100,
    "stats": {
      "transfers": 13,
      "holders_gt10": 53
    }
  }
}