{
  "ethereum": {
    "last_block": 24814810,
    "stats": {
      "transfers": 68,
      "holders_gt10": 537
    }
  },
  "arbitrum": {
    "last_block": 449361559,
    "stats": {
      "transfers": 340,
      "holders_gt10": 136
    }
  },
  "polygon": {
    "last_block": 85143313,
    "stats": {
      "transfers": 2,
      "holders_gt10": 50
    }
  },
  "last_full_scan": "2026-04-05",
  "last_scan": "2026-04-05T17:01:34Z",
  "mode": "INCREMENTAL",
  "base": {
    "last_block": 44309569,
    "stats": {
      "transfers": 4924,
      "holders_gt10": 71
    }
  },
  "optimism": {
    "last_block": 149904652,
    "stats": {
      "transfers": 125,
      "holders_gt10": 58
    }
  }
}